pulser_qek/__init__.py
pulser_qek/add.py
pulser_qek/pulse_qek.py
pulser_qek/subtract.py
pulser_qek/extras/__init__.py
pulser_qek/extras/divide.py
pulser_qek/extras/multiply.py
pulser_qek-0.0.1.dist-info/METADATA
pulser_qek-0.0.1.dist-info/WHEEL
pulser_qek-0.0.1.dist-info/top_level.txt
pulser_qek-0.0.1.dist-info/RECORD
